CHANGES.rst
README.md
drf_viewset_profiler/__init__.py
drf_viewset_profiler/decorators.py
drf_viewset_profiler/middleware.py
drf_viewset_profiler/output.py
drf_viewset_profiler/utils.py
drf_viewset_profiler-0.4.0.dist-info/LICENSE
drf_viewset_profiler-0.4.0.dist-info/METADATA
drf_viewset_profiler-0.4.0.dist-info/WHEEL
drf_viewset_profiler-0.4.0.dist-info/RECORD
