Metadata-Version: 2.1
Name: drf-viewset-profiler
Version: 0.4.0
Summary: Lib to profile all methods from a viewset line by line
Home-page: https://github.com/fvlima/drf-viewset-profiler
License: MIT
Keywords: django rest framework,drf,drf viewset,viewset line profiler,profiler
Author: Frederico V Lima
Author-email: frederico.vieira@gmail.com
Requires-Python: >=3.8,<4.0
Classifier: Development Status :: 5 - Production/Stable
Classifier: Intended Audience :: Developers
Classifier: License :: OSI Approved :: MIT License
Classifier: Operating System :: OS Independent
Classifier: Programming Language :: Python
Classifier: Programming Language :: Python :: 3
Classifier: Programming Language :: Python :: 3.8
Classifier: Programming Language :: Python :: 3.9
Classifier: Programming Language :: Python :: 3.10
Classifier: Programming Language :: Python :: 3.11
Classifier: Programming Language :: Python :: 3.12
Classifier: Programming Language :: Python :: Implementation :: CPython
Classifier: Topic :: Software Development :: Testing
Requires-Dist: Cython (>=3.0,<4.0)
Requires-Dist: line_profiler (>=4.0,<5.0)
Project-URL: Repository, https://github.com/fvlima/drf-viewset-profiler
